[
    {
        "url": "https://www.eventlokale.ch",
        "h1": "Dein Moment. Dein Event.",
        "results_count": "N/A"
    },
    {
        "url": "https://www.eventlokale.ch/site/_redaktionell/52/eventmagazin.html?suche_tag1=Eventtalks",
        "h1": "Eventmagazin",
        "results_count": "N/A"
    },
    {
        "url": "https://www.eventlokale.ch/site/_redaktionell/52/eventmagazin.html?suche_tag1=Eventideen",
        "h1": "Eventmagazin",
        "results_count": "N/A"
    },
    {
        "url": "https://www.eventlokale.ch/site/_redaktionell/52/eventmagazin.html",
        "h1": "Eventmagazin",
        "results_count": "N/A"
    },
    {
        "url": "https://www.eventlokale.ch/site/_redaktionell/52/eventmagazin.html?suche_tag1=Gewinnspiel",
        "h1": "Eventmagazin",
        "results_count": "N/A"
    },
    {
        "url": "https://www.eventlokale.ch/site/_redaktionell/52/eventmagazin.html?suche_tag1=Inspiration",
        "h1": "Eventmagazin",
        "results_count": "N/A"
    },
    {
        "url": "https://www.eventlokale.ch/site/_redaktionell/52/eventmagazin.html?suche_tag1=Eventnews",
        "h1": "Eventmagazin",
        "results_count": "N/A"
    },
    {
        "url": "https://www.eventlokale.ch/site/_redaktionell/52/eventmagazin.html?suche_tag1=Trends",
        "h1": "Eventmagazin",
        "results_count": "N/A"
    },
    {
        "url": "https://www.eventlokale.ch/site/_redaktionell/52/eventmagazin.html?suche_tag1=Promotions",
        "h1": "Eventmagazin",
        "results_count": "N/A"
    },
    {
        "url": "https://www.eventlokale.ch/site/_redaktionell/52/eventmagazin.html?suche_tag1=Swiss Location Award",
        "h1": "Eventmagazin",
        "results_count": "N/A"
    },
    {
        "url": "https://www.eventlokale.ch/site/_redaktionell/52/eventmagazin.html?suche_tag1=Tutorials",
        "h1": "Eventmagazin",
        "results_count": "N/A"
    },
    {
        "url": "https://www.eventlokale.ch/swisslocationaward2022_ausgezeichnet",
        "h1": "Swiss LocationAward 2022",
        "results_count": "N/A"
    },
    {
        "url": "https://www.eventlokale.ch/swisslocationaward2022_ausgezeichnet/kongresslocations_konferenzhaeuser",
        "h1": "Swiss LocationAward 2022",
        "results_count": "N/A"
    },
    {
        "url": "https://www.eventlokale.ch/swisslocationaward2022_ausgezeichnet/meetinglocations_sitzungszimmer",
        "h1": "Swiss LocationAward 2022",
        "results_count": "N/A"
    },
    {
        "url": "https://www.eventlokale.ch/swisslocationaward2022_ausgezeichnet/tagungslocations_seminarhotels",
        "h1": "Swiss LocationAward 2022",
        "results_count": "N/A"
    },
    {
        "url": "https://www.eventlokale.ch/swisslocationaward2022_ausgezeichnet/eventraeume",
        "h1": "Swiss LocationAward 2022",
        "results_count": "N/A"
    },
    {
        "url": "https://www.eventlokale.ch/swisslocationaward2022_ausgezeichnet/eventhallen_messehallen",
        "h1": "Swiss LocationAward 2022",
        "results_count": "N/A"
    },
    {
        "url": "https://www.eventlokale.ch/swisslocationaward2022_ausgezeichnet/eventlocations",
        "h1": "Swiss LocationAward 2022",
        "results_count": "N/A"
    },
    {
        "url": "https://www.eventlokale.ch/swisslocationaward2022_ausgezeichnet/hochzeitslocations",
        "h1": "Swiss LocationAward 2022",
        "results_count": "N/A"
    },
    {
        "url": "https://www.eventlokale.ch/swisslocationaward2022_ausgezeichnet/erlebnislocations",
        "h1": "Swiss LocationAward 2022",
        "results_count": "N/A"
    },
    {
        "url": "https://www.eventlokale.ch/site/de/swisslocationaward2023_ausgezeichnet",
        "h1": "Swiss LocationAward 2023",
        "results_count": "10 Award Kategorien"
    },
    {
        "url": "https://www.eventlokale.ch/swisslocationaward2022_ausgezeichnet/bars_clubs",
        "h1": "Swiss LocationAward 2022",
        "results_count": "N/A"
    },
    {
        "url": "https://www.eventlokale.ch/site/en/swisslocationaward2023_awarded",
        "h1": "Swiss LocationAward 2023",
        "results_count": "10 award categories"
    },
    {
        "url": "https://www.eventlokale.ch/site/_redaktionell/51/Eventjobs.html",
        "h1": "Eventjobs",
        "results_count": "N/A"
    },
    {
        "url": "https://www.eventlokale.ch/site/fr/swisslocationaward2023_distingue",
        "h1": "Swiss LocationAward 2023",
        "results_count": "10 catégories de l’Award"
    },
    {
        "url": "https://www.eventlokale.ch/swisslocationaward2022_ausgezeichnet/genusslocations_restaurants",
        "h1": "Swiss LocationAward 2022",
        "results_count": "N/A"
    },
    {
        "url": "https://www.eventlokale.ch/site/it/swisslocationaward2023_premiate",
        "h1": "Swiss LocationAward 2023",
        "results_count": "10 categorie dell’Award"
    },
    {
        "url": "https://www.eventlokale.ch/site/de/swisslocationaward2023_ausgezeichnet/meetinglocations_sitzungszimmer",
        "h1": "Swiss LocationAward 2023",
        "results_count": "106 Locations"
    },
    {
        "url": "https://www.eventlokale.ch/site/de/swisslocationaward2023_ausgezeichnet/tagungslocations_seminarhotels",
        "h1": "Swiss LocationAward 2023",
        "results_count": "68 Locations"
    },
    {
        "url": "https://www.eventlokale.ch/site/it/swisslocationaward2023_premiate/sale_di_riunione",
        "h1": "Swiss LocationAward 2023",
        "results_count": "106 location"
    },
    {
        "url": "https://www.eventlokale.ch/site/en/swisslocationaward2023_awarded/meeting_locations",
        "h1": "Swiss LocationAward 2023",
        "results_count": "106 Locations"
    },
    {
        "url": "https://www.eventlokale.ch/site/fr/swisslocationaward2023_distingue/lieux_de_reunion",
        "h1": "Swiss LocationAward 2023",
        "results_count": "106 Lieux"
    },
    {
        "url": "https://www.eventlokale.ch/site/en/swisslocationaward2023_awarded/conference_locations",
        "h1": "Swiss LocationAward 2023",
        "results_count": "68 Locations"
    },
    {
        "url": "https://www.eventlokale.ch/site/fr/swisslocationaward2023_distingue/lieux_de_conference",
        "h1": "Swiss LocationAward 2023",
        "results_count": "68 Lieux"
    },
    {
        "url": "https://www.eventlokale.ch/site/de/swisslocationaward2023_ausgezeichnet/kongresslocations_konferenzhaeuser",
        "h1": "Swiss LocationAward 2023",
        "results_count": "39 Locations"
    },
    {
        "url": "https://www.eventlokale.ch/site/it/swisslocationaward2023_premiate/sedi_di_conferenze",
        "h1": "Swiss LocationAward 2023",
        "results_count": "68 location"
    },
    {
        "url": "https://www.eventlokale.ch/site/en/swisslocationaward2023_awarded/congress_venues",
        "h1": "Swiss LocationAward 2023",
        "results_count": "39 Locations"
    },
    {
        "url": "https://www.eventlokale.ch/site/fr/swisslocationaward2023_distingue/lieux_de_congres",
        "h1": "Swiss LocationAward 2023",
        "results_count": "39 Lieux"
    },
    {
        "url": "https://www.eventlokale.ch/site/it/swisslocationaward2023_premiate/sedi_di_congressi",
        "h1": "Swiss LocationAward 2023",
        "results_count": "39 location"
    },
    {
        "url": "https://www.eventlokale.ch/site/de/swisslocationaward2023_ausgezeichnet/eventraeume",
        "h1": "Swiss LocationAward 2023",
        "results_count": "142 Locations"
    },
    {
        "url": "https://www.eventlokale.ch/site/en/swisslocationaward2023_awarded/event_rooms",
        "h1": "Swiss LocationAward 2023",
        "results_count": "142 Locations"
    },
    {
        "url": "https://www.eventlokale.ch/site/de/swisslocationaward2023_ausgezeichnet/eventlocations",
        "h1": "Swiss LocationAward 2023",
        "results_count": "79 Locations"
    },
    {
        "url": "https://www.eventlokale.ch/site/fr/swisslocationaward2023_distingue/salles_de_evenements",
        "h1": "Swiss LocationAward 2023",
        "results_count": "142 Lieux"
    },
    {
        "url": "https://www.eventlokale.ch/site/it/swisslocationaward2023_premiate/sale_per_eventi",
        "h1": "Swiss LocationAward 2023",
        "results_count": "142 location"
    },
    {
        "url": "https://www.eventlokale.ch/site/en/swisslocationaward2023_awarded/event_locations",
        "h1": "Swiss LocationAward 2023",
        "results_count": "79 Locations"
    },
    {
        "url": "https://www.eventlokale.ch/site/fr/swisslocationaward2023_distingue/lieux_d_evenements",
        "h1": "Swiss LocationAward 2023",
        "results_count": "79 Lieux"
    },
    {
        "url": "https://www.eventlokale.ch/site/it/swisslocationaward2023_premiate/location_per_eventi",
        "h1": "Swiss LocationAward 2023",
        "results_count": "79 location"
    },
    {
        "url": "https://www.eventlokale.ch/site/de/swisslocationaward2023_ausgezeichnet/eventhallen_messehallen",
        "h1": "Swiss LocationAward 2023",
        "results_count": "33 Locations"
    },
    {
        "url": "https://www.eventlokale.ch/site/fr/swisslocationaward2023_distingue/halles_d_evenements",
        "h1": "Swiss LocationAward 2023",
        "results_count": "33 Lieux"
    },
    {
        "url": "https://www.eventlokale.ch/site/en/swisslocationaward2023_awarded/event_halls",
        "h1": "Swiss LocationAward 2023",
        "results_count": "33 Locations"
    },
    {
        "url": "https://www.eventlokale.ch/site/it/swisslocationaward2023_premiate/arene_per_eventi",
        "h1": "Swiss LocationAward 2023",
        "results_count": "33 location"
    },
    {
        "url": "https://www.eventlokale.ch/site/de/swisslocationaward2023_ausgezeichnet/sportstadien",
        "h1": "Swiss LocationAward 2023",
        "results_count": "10 Award Kategorien"
    },
    {
        "url": "https://www.eventlokale.ch/site/en/swisslocationaward2023_awarded/sports_stadiums",
        "h1": "Swiss LocationAward 2023",
        "results_count": "10 award categories"
    },
    {
        "url": "https://www.eventlokale.ch/site/it/swisslocationaward2023_premiate/stadi_sportivi",
        "h1": "Swiss LocationAward 2023",
        "results_count": "10 categorie dell’Award"
    },
    {
        "url": "https://www.eventlokale.ch/site/de/swisslocationaward2023_ausgezeichnet/hochzeitslocations",
        "h1": "Swiss LocationAward 2023",
        "results_count": "149 Locations"
    },
    {
        "url": "https://www.eventlokale.ch/site/fr/swisslocationaward2023_distingue/stades_sportifs",
        "h1": "Swiss LocationAward 2023",
        "results_count": "10 catégories de l’Award"
    },
    {
        "url": "https://www.eventlokale.ch/site/en/swisslocationaward2023_awarded/wedding_venues",
        "h1": "Swiss LocationAward 2023",
        "results_count": "149 Locations"
    },
    {
        "url": "https://www.eventlokale.ch/site/fr/swisslocationaward2023_distingue/lieux_de_mariage",
        "h1": "Swiss LocationAward 2023",
        "results_count": "149 Lieux"
    },
    {
        "url": "https://www.eventlokale.ch/site/it/swisslocationaward2023_premiate/location_per_matrimoni",
        "h1": "Swiss LocationAward 2023",
        "results_count": "149 location"
    },
    {
        "url": "https://www.eventlokale.ch/site/de/swisslocationaward2023_ausgezeichnet/erlebnislocations",
        "h1": "Swiss LocationAward 2023",
        "results_count": "172 Locations"
    },
    {
        "url": "https://www.eventlokale.ch/site/fr/swisslocationaward2023_distingue/lieux_d_experience",
        "h1": "Swiss LocationAward 2023",
        "results_count": "172 Lieux"
    },
    {
        "url": "https://www.eventlokale.ch/site/it/swisslocationaward2023_premiate/location_di_esperienze",
        "h1": "Swiss LocationAward 2023",
        "results_count": "172 location"
    },
    {
        "url": "https://www.eventlokale.ch/site/en/swisslocationaward2023_awarded/experience_venues",
        "h1": "Swiss LocationAward 2023",
        "results_count": "172 Locations"
    },
    {
        "url": "https://www.eventlokale.ch/site/en/swisslocationaward2023_awarded/culinary_locations",
        "h1": "Swiss LocationAward 2023",
        "results_count": "323 Locations"
    },
    {
        "url": "https://www.eventlokale.ch/site/de/swisslocationaward2023_ausgezeichnet/bars_clubs",
        "h1": "Swiss LocationAward 2023",
        "results_count": "88 Locations"
    },
    {
        "url": "https://www.eventlokale.ch/site/en/swisslocationaward2023_awarded/bars_clubs",
        "h1": "Swiss LocationAward 2023",
        "results_count": "88 Locations"
    },
    {
        "url": "https://www.eventlokale.ch/site/fr/swisslocationaward2023_distingue/localites_culinaires",
        "h1": "Swiss LocationAward 2023",
        "results_count": "323 Lieux"
    },
    {
        "url": "https://www.eventlokale.ch/site/de/swisslocationaward2023_ausgezeichnet/genusslocations_restaurants",
        "h1": "Swiss LocationAward 2023",
        "results_count": "323 Locations"
    },
    {
        "url": "https://www.eventlokale.ch/site/it/swisslocationaward2023_premiate/localita_culinarie",
        "h1": "Swiss LocationAward 2023",
        "results_count": "323 location"
    },
    {
        "url": "https://www.eventlokale.ch/site/fr/swisslocationaward2023_distingue/bars_clubs",
        "h1": "Swiss LocationAward 2023",
        "results_count": "88 Lieux"
    },
    {
        "url": "https://www.eventlokale.ch/site/de/swisslocationaward2024_ausgezeichnet",
        "h1": "Swiss LocationAward 2024",
        "results_count": "11 Award Kategorien"
    },
    {
        "url": "https://www.eventlokale.ch/site/en/swisslocationaward2024_awarded",
        "h1": "Swiss LocationAward 2024",
        "results_count": "11 award categories"
    },
    {
        "url": "https://www.eventlokale.ch/site/fr/swisslocationaward2024_distingue",
        "h1": "Swiss LocationAward 2024",
        "results_count": "11 catégories de l’Award"
    },
    {
        "url": "https://www.eventlokale.ch/site/it/swisslocationaward2023_premiate/bar_club",
        "h1": "Swiss LocationAward 2023",
        "results_count": "88 location"
    },
    {
        "url": "https://www.eventlokale.ch/site/it/swisslocationaward2024_premiate",
        "h1": "Swiss LocationAward 2024",
        "results_count": "11 categorie dell’Award"
    },
    {
        "url": "https://www.eventlokale.ch/site/en/swisslocationaward2024_awarded/meeting_locations",
        "h1": "Swiss LocationAward 2024",
        "results_count": "118 Locations"
    },
    {
        "url": "https://www.eventlokale.ch/site/fr/swisslocationaward2024_distingue/lieux_de_reunion",
        "h1": "Swiss LocationAward 2024",
        "results_count": "118 Lieux"
    },
    {
        "url": "https://www.eventlokale.ch/site/de/swisslocationaward2024_ausgezeichnet/meetinglocations_sitzungszimmer",
        "h1": "Swiss LocationAward 2024",
        "results_count": "118 Locations"
    },
    {
        "url": "https://www.eventlokale.ch/site/it/swisslocationaward2024_premiate/sale_di_riunione",
        "h1": "Swiss LocationAward 2024",
        "results_count": "118 location"
    },
    {
        "url": "https://www.eventlokale.ch/site/de/swisslocationaward2024_ausgezeichnet/tagungslocations_seminarhotels",
        "h1": "Swiss LocationAward 2024",
        "results_count": "87 Locations"
    },
    {
        "url": "https://www.eventlokale.ch/site/de/swisslocationaward2024_ausgezeichnet/kongresslocations_konferenzhaeuser",
        "h1": "Swiss LocationAward 2024",
        "results_count": "41 Locations"
    },
    {
        "url": "https://www.eventlokale.ch/site/fr/swisslocationaward2024_distingue/lieux_de_conference",
        "h1": "Swiss LocationAward 2024",
        "results_count": "87 Lieux"
    },
    {
        "url": "https://www.eventlokale.ch/site/it/swisslocationaward2024_premiate/sedi_di_conferenze",
        "h1": "Swiss LocationAward 2024",
        "results_count": "87 location"
    },
    {
        "url": "https://www.eventlokale.ch/site/en/swisslocationaward2024_awarded/congress_venues",
        "h1": "Swiss LocationAward 2024",
        "results_count": "41 Locations"
    },
    {
        "url": "https://www.eventlokale.ch/site/en/swisslocationaward2024_awarded/conference_locations",
        "h1": "Swiss LocationAward 2024",
        "results_count": "87 Locations"
    },
    {
        "url": "https://www.eventlokale.ch/site/fr/swisslocationaward2024_distingue/lieux_de_congres",
        "h1": "Swiss LocationAward 2024",
        "results_count": "41 Lieux"
    },
    {
        "url": "https://www.eventlokale.ch/site/it/swisslocationaward2024_premiate/sedi_di_congressi",
        "h1": "Swiss LocationAward 2024",
        "results_count": "41 location"
    },
    {
        "url": "https://www.eventlokale.ch/site/fr/swisslocationaward2024_distingue/salles_de_evenements",
        "h1": "Swiss LocationAward 2024",
        "results_count": "160 Lieux"
    },
    {
        "url": "https://www.eventlokale.ch/site/de/swisslocationaward2024_ausgezeichnet/eventraeume",
        "h1": "Swiss LocationAward 2024",
        "results_count": "160 Locations"
    },
    {
        "url": "https://www.eventlokale.ch/site/en/swisslocationaward2024_awarded/event_rooms",
        "h1": "Swiss LocationAward 2024",
        "results_count": "160 Locations"
    },
    {
        "url": "https://www.eventlokale.ch/site/de/swisslocationaward2024_ausgezeichnet/eventlocations",
        "h1": "Swiss LocationAward 2024",
        "results_count": "100 Locations"
    },
    {
        "url": "https://www.eventlokale.ch/site/it/swisslocationaward2024_premiate/sale_per_eventi",
        "h1": "Swiss LocationAward 2024",
        "results_count": "160 location"
    },
    {
        "url": "https://www.eventlokale.ch/site/en/swisslocationaward2024_awarded/event_locations",
        "h1": "Swiss LocationAward 2024",
        "results_count": "100 Locations"
    },
    {
        "url": "https://www.eventlokale.ch/site/de/swisslocationaward2024_ausgezeichnet/eventhallen_messehallen",
        "h1": "Swiss LocationAward 2024",
        "results_count": "33 Locations"
    },
    {
        "url": "https://www.eventlokale.ch/site/it/swisslocationaward2024_premiate/location_per_eventi",
        "h1": "Swiss LocationAward 2024",
        "results_count": "100 location"
    },
    {
        "url": "https://www.eventlokale.ch/site/en/swisslocationaward2024_awarded/event_halls",
        "h1": "Swiss LocationAward 2024",
        "results_count": "33 Locations"
    },
    {
        "url": "https://www.eventlokale.ch/site/fr/swisslocationaward2024_distingue/lieux_d_evenements",
        "h1": "Swiss LocationAward 2024",
        "results_count": "100 Lieux"
    },
    {
        "url": "https://www.eventlokale.ch/site/fr/swisslocationaward2024_distingue/halles_d_evenements",
        "h1": "Swiss LocationAward 2024",
        "results_count": "N/A"
    },
    {
        "url": "https://www.eventlokale.ch/site/it/swisslocationaward2024_premiate/arene_per_eventi",
        "h1": "Swiss LocationAward 2024",
        "results_count": "N/A"
    },
    {
        "url": "https://www.eventlokale.ch/site/de/swisslocationaward2024_ausgezeichnet/sportstadien",
        "h1": "Swiss LocationAward 2024",
        "results_count": "N/A"
    }
]