[
    {
        "url": "https://www.eventlokale.ch/site/it/swisslocationaward2024_premiate/stadi_sportivi",
        "h1": "Swiss LocationAward 2024",
        "results_count": "27 location"
    },
    {
        "url": "https://www.eventlokale.ch/site/fr/swisslocationaward2024_distingue/stades_sportifs",
        "h1": "Swiss LocationAward 2024",
        "results_count": "27 Lieux"
    },
    {
        "url": "https://www.eventlokale.ch/site/en/swisslocationaward2024_awarded/sports_stadiums",
        "h1": "Swiss LocationAward 2024",
        "results_count": "27 Locations"
    },
    {
        "url": "https://www.eventlokale.ch/site/en/swisslocationaward2024_awarded/wedding_venues",
        "h1": "Swiss LocationAward 2024",
        "results_count": "135 Locations"
    },
    {
        "url": "https://www.eventlokale.ch/site/de/swisslocationaward2024_ausgezeichnet/hochzeitslocations",
        "h1": "Swiss LocationAward 2024",
        "results_count": "135 Locations"
    },
    {
        "url": "https://www.eventlokale.ch/site/fr/swisslocationaward2024_distingue/lieux_de_mariage",
        "h1": "Swiss LocationAward 2024",
        "results_count": "135 Lieux"
    },
    {
        "url": "https://www.eventlokale.ch/site/it/swisslocationaward2024_premiate/location_per_matrimoni",
        "h1": "Swiss LocationAward 2024",
        "results_count": "135 location"
    },
    {
        "url": "https://www.eventlokale.ch/site/de/swisslocationaward2024_ausgezeichnet/erlebnislocations",
        "h1": "Swiss LocationAward 2024",
        "results_count": "154 Locations"
    },
    {
        "url": "https://www.eventlokale.ch/site/en/swisslocationaward2024_awarded/experience_venues",
        "h1": "Swiss LocationAward 2024",
        "results_count": "154 Locations"
    },
    {
        "url": "https://www.eventlokale.ch/site/it/swisslocationaward2024_premiate/location_di_esperienze",
        "h1": "Swiss LocationAward 2024",
        "results_count": "154 location"
    },
    {
        "url": "https://www.eventlokale.ch/site/fr/swisslocationaward2024_distingue/lieux_d_experience",
        "h1": "Swiss LocationAward 2024",
        "results_count": "154 Lieux"
    },
    {
        "url": "https://www.eventlokale.ch/site/de/swisslocationaward2024_ausgezeichnet/genusslocations_restaurants",
        "h1": "Swiss LocationAward 2024",
        "results_count": "324 Locations"
    },
    {
        "url": "https://www.eventlokale.ch/site/de/swisslocationaward2024_ausgezeichnet/bars_clubs",
        "h1": "Swiss LocationAward 2024",
        "results_count": "96 Locations"
    },
    {
        "url": "https://www.eventlokale.ch/site/en/swisslocationaward2024_awarded/culinary_locations",
        "h1": "Swiss LocationAward 2024",
        "results_count": "324 Locations"
    },
    {
        "url": "https://www.eventlokale.ch/site/en/swisslocationaward2024_awarded/bars_clubs",
        "h1": "Swiss LocationAward 2024",
        "results_count": "96 Locations"
    },
    {
        "url": "https://www.eventlokale.ch/site/fr/swisslocationaward2024_distingue/localites_culinaires",
        "h1": "Swiss LocationAward 2024",
        "results_count": "324 Lieux"
    },
    {
        "url": "https://www.eventlokale.ch/site/fr/swisslocationaward2024_distingue/bars_clubs",
        "h1": "Swiss LocationAward 2024",
        "results_count": "96 Lieux"
    },
    {
        "url": "https://www.eventlokale.ch/site/it/swisslocationaward2024_premiate/localita_culinarie",
        "h1": "Swiss LocationAward 2024",
        "results_count": "324 location"
    },
    {
        "url": "https://www.eventlokale.ch/site/it/swisslocationaward2024_premiate/bar_club",
        "h1": "Swiss LocationAward 2024",
        "results_count": "96 location"
    },
    {
        "url": "https://www.eventlokale.ch/site/extern/about_us.html",
        "h1": "Willkommen auf dem grössten Eventportal der Schweiz.",
        "results_count": "N/A"
    },
    {
        "url": "https://www.eventlokale.ch/site/extern/werbemoeglichkeiten_mailing.html",
        "h1": "Eventmagazin Newsletter",
        "results_count": "N/A"
    },
    {
        "url": "https://www.eventlokale.ch/site/extern/eventjob_inserieren.html",
        "h1": "Die perfekten Mitarbeiter/innen finden & durchstarten",
        "results_count": "N/A"
    },
    {
        "url": "https://www.eventlokale.ch/site/extern/impressum.html",
        "h1": "Allgemeine Geschäftsbedingungen",
        "results_count": "N/A"
    },
    {
        "url": "https://www.eventlokale.ch/site/extern/werbemoeglichkeiten.html",
        "h1": "Erreiche die Eventwelt mit deinen Angeboten",
        "results_count": "N/A"
    },
    {
        "url": "https://www.eventlokale.ch/site/extern/werbemoeglichkeiten_eintraege.html",
        "h1": "Location- und Dienstleister Einträge auf eventlokale.ch",
        "results_count": "N/A"
    },
    {
        "url": "https://www.eventlokale.ch/site/extern/werbemoeglichkeiten_werbeformate.html",
        "h1": "Boosts & Werbeflächen",
        "results_count": "N/A"
    },
    {
        "url": "https://www.eventlokale.ch/site/de/swisslocationaward_facts_and_figures",
        "h1": "Swiss Location Awardby eventlokale.ch",
        "results_count": "N/A"
    },
    {
        "url": "https://www.eventlokale.ch/site/fr/swisslocationaward_facts_and_figures",
        "h1": "Swiss Location Awardby eventlokale.ch",
        "results_count": "N/A"
    },
    {
        "url": "https://www.eventlokale.ch/site/en/swisslocationaward_facts_and_figures",
        "h1": "Swiss Location Awardby eventlokale.ch",
        "results_count": "N/A"
    },
    {
        "url": "https://www.eventlokale.ch/site/it/swisslocationaward_facts_and_figures",
        "h1": "Swiss Location Awardby eventlokale.ch",
        "results_count": "N/A"
    },
    {
        "url": "https://www.eventlokale.ch/site/en/swisslocationaward_overview",
        "h1": "Swiss Location Awardby eventlokale.ch",
        "results_count": "N/A"
    },
    {
        "url": "https://www.eventlokale.ch/site/en/swisslocationaward_retrospective",
        "h1": "Swiss Location Awardby eventlokale.ch",
        "results_count": "N/A"
    },
    {
        "url": "https://www.eventlokale.ch/site/de/swisslocationaward_uebersicht",
        "h1": "Swiss Location Awardby eventlokale.ch",
        "results_count": "N/A"
    },
    {
        "url": "https://www.eventlokale.ch/site/it/swisslocationaward_visione_dinsieme",
        "h1": "Swiss Location Awardby eventlokale.ch",
        "results_count": "N/A"
    },
    {
        "url": "https://www.eventlokale.ch/site/it/swisslocationaward_retrospettiva",
        "h1": "Swiss Location Awardby eventlokale.ch",
        "results_count": "N/A"
    },
    {
        "url": "https://www.eventlokale.ch/site/fr/swisslocationaward_retrospective",
        "h1": "Swiss Location Awardby eventlokale.ch",
        "results_count": "N/A"
    },
    {
        "url": "https://www.eventlokale.ch/site/de/swisslocationaward_rueckblick",
        "h1": "Swiss Location Awardby eventlokale.ch",
        "results_count": "N/A"
    },
    {
        "url": "https://www.eventlokale.ch/site/fr/swisslocationaward_vue_densemble",
        "h1": "Swiss Location Awardby eventlokale.ch",
        "results_count": "N/A"
    },
    {
        "url": "https://www.eventlokale.ch/locations",
        "h1": "Locations für deinen Event in der Schweiz",
        "results_count": "4960 Resultate"
    },
    {
        "url": "https://www.eventlokale.ch/locations/vereinsanlass",
        "h1": "Locations für Vereinsanlass in der Schweiz",
        "results_count": "470 Resultate"
    },
    {
        "url": "https://www.eventlokale.ch/locations/kongress",
        "h1": "Locations für Kongress in der Schweiz",
        "results_count": "223 Resultate"
    },
    {
        "url": "https://www.eventlokale.ch/locations/firmenanlass",
        "h1": "Locations für Firmenanlass in der Schweiz",
        "results_count": "1628 Resultate"
    },
    {
        "url": "https://www.eventlokale.ch/locations/gv_versammlung",
        "h1": "Locations für Versammlung, GV in der Schweiz",
        "results_count": "456 Resultate"
    },
    {
        "url": "https://www.eventlokale.ch/locations/meeting",
        "h1": "Locations für Meeting in der Schweiz",
        "results_count": "684 Resultate"
    },
    {
        "url": "https://www.eventlokale.ch/locations/tagung",
        "h1": "Locations für Tagung in der Schweiz",
        "results_count": "693 Resultate"
    },
    {
        "url": "https://www.eventlokale.ch/locations/geburtstag",
        "h1": "Locations für Geburtstag in der Schweiz",
        "results_count": "1055 Resultate"
    },
    {
        "url": "https://www.eventlokale.ch/locations/hochzeit",
        "h1": "Locations für Hochzeit in der Schweiz",
        "results_count": "848 Resultate"
    },
    {
        "url": "https://www.eventlokale.ch/locations/familienfeier",
        "h1": "Locations für Familienfeier in der Schweiz",
        "results_count": "928 Resultate"
    },
    {
        "url": "https://www.eventlokale.ch/locations/privatanlass",
        "h1": "Locations für Privatanlass in der Schweiz",
        "results_count": "1071 Resultate"
    },
    {
        "url": "https://www.eventlokale.ch/locations/teamevent",
        "h1": "Locations für Teamevent in der Schweiz",
        "results_count": "726 Resultate"
    },
    {
        "url": "https://www.eventlokale.ch/locations/apero",
        "h1": "Locations für Apéro in der Schweiz",
        "results_count": "719 Resultate"
    },
    {
        "url": "https://www.eventlokale.ch/locations/party",
        "h1": "Locations für Party, Feier in der Schweiz",
        "results_count": "388 Resultate"
    },
    {
        "url": "https://www.eventlokale.ch/locations/konzert",
        "h1": "Locations für Konzert in der Schweiz",
        "results_count": "514 Resultate"
    },
    {
        "url": "https://www.eventlokale.ch/locations/theater-1",
        "h1": "Locations für Theater in der Schweiz",
        "results_count": "59 Resultate"
    },
    {
        "url": "https://www.eventlokale.ch/locations/messe_ausstellung",
        "h1": "Locations für Messe, Ausstellung in der Schweiz",
        "results_count": "84 Resultate"
    },
    {
        "url": "https://www.eventlokale.ch/locations/klassentreffen",
        "h1": "Locations für Klassentreffen in der Schweiz",
        "results_count": "327 Resultate"
    },
    {
        "url": "https://www.eventlokale.ch/locations/party-1",
        "h1": "Locations für Party in der Schweiz",
        "results_count": "461 Resultate"
    },
    {
        "url": "https://www.eventlokale.ch/locations/weihnachtsfeier",
        "h1": "Locations für Weihnachtsfeier in der Schweiz",
        "results_count": "496 Resultate"
    },
    {
        "url": "https://www.eventlokale.ch/locations/sportanlass",
        "h1": "Locations für Sportanlass in der Schweiz",
        "results_count": "108 Resultate"
    },
    {
        "url": "https://www.eventlokale.ch/locations/oeffentlicher_anlass",
        "h1": "Locations für Öffentlicher Anlass in der Schweiz",
        "results_count": "480 Resultate"
    },
    {
        "url": "https://www.eventlokale.ch/locations/bar_club",
        "h1": "Bar, Club für deinen Event in der Schweiz",
        "results_count": "359 Resultate"
    },
    {
        "url": "https://www.eventlokale.ch/locations/hochzeitslocation",
        "h1": "Hochzeitslocation für deinen Event in der Schweiz",
        "results_count": "475 Resultate"
    },
    {
        "url": "https://www.eventlokale.ch/locations/eventlocation",
        "h1": "Eventlocation für deinen Event in der Schweiz",
        "results_count": "2247 Resultate"
    },
    {
        "url": "https://www.eventlokale.ch/locations/hotel_seminarhotel",
        "h1": "Hotel, Seminarhotel für deinen Event in der Schweiz",
        "results_count": "1092 Resultate"
    },
    {
        "url": "https://www.eventlokale.ch/locations/partyraum",
        "h1": "Partyraum für deinen Event in der Schweiz",
        "results_count": "227 Resultate"
    },
    {
        "url": "https://www.eventlokale.ch/locations/restaurant-1",
        "h1": "Restaurant für deinen Event in der Schweiz",
        "results_count": "1413 Resultate"
    },
    {
        "url": "https://www.eventlokale.ch/locations/kongresszentrum",
        "h1": "Kongresszentrum für deinen Event in der Schweiz",
        "results_count": "178 Resultate"
    },
    {
        "url": "https://www.eventlokale.ch/locations/schloss",
        "h1": "Schloss für deinen Event in der Schweiz",
        "results_count": "119 Resultate"
    },
    {
        "url": "https://www.eventlokale.ch/locations/waldhuette",
        "h1": "Waldhütte für deinen Event in der Schweiz",
        "results_count": "166 Resultate"
    },
    {
        "url": "https://www.eventlokale.ch/locations/bauernhof_scheune",
        "h1": "Bauernhof, Scheune für deinen Event in der Schweiz",
        "results_count": "167 Resultate"
    },
    {
        "url": "https://www.eventlokale.ch/locations/berghuette_alphuette",
        "h1": "Berghütte, Alphütte für deinen Event in der Schweiz",
        "results_count": "137 Resultate"
    },
    {
        "url": "https://www.eventlokale.ch/locations/brauerei_weingut",
        "h1": "Brauerei, Weingut für deinen Event in der Schweiz",
        "results_count": "68 Resultate"
    },
    {
        "url": "https://www.eventlokale.ch/locations/burg",
        "h1": "Burg für deinen Event in der Schweiz",
        "results_count": "19 Resultate"
    },
    {
        "url": "https://www.eventlokale.ch/locations/cafe",
        "h1": "Café für deinen Event in der Schweiz",
        "results_count": "101 Resultate"
    },
    {
        "url": "https://www.eventlokale.ch/locations/hoehle_festung",
        "h1": "Höhle, Festung für deinen Event in der Schweiz",
        "results_count": "7 Resultate"
    },
    {
        "url": "https://www.eventlokale.ch/locations/erlebnis_kreatives",
        "h1": "Erlebnis, Kreatives für deinen Event in der Schweiz",
        "results_count": "481 Resultate"
    },
    {
        "url": "https://www.eventlokale.ch/locations/fabrikhalle",
        "h1": "Fabrikhalle für deinen Event in der Schweiz",
        "results_count": "66 Resultate"
    },
    {
        "url": "https://www.eventlokale.ch/locations/casino",
        "h1": "Casino für deinen Event in der Schweiz",
        "results_count": "9 Resultate"
    },
    {
        "url": "https://www.eventlokale.ch/locations/eventhalle",
        "h1": "Eventhalle für deinen Event in der Schweiz",
        "results_count": "189 Resultate"
    },
    {
        "url": "https://www.eventlokale.ch/locations/fahrbare_location",
        "h1": "Fahrbare Location für deinen Event in der Schweiz",
        "results_count": "29 Resultate"
    },
    {
        "url": "https://www.eventlokale.ch/locations/messehalle",
        "h1": "Messehalle für deinen Event in der Schweiz",
        "results_count": "122 Resultate"
    },
    {
        "url": "https://www.eventlokale.ch/locations/garten_treibhaus",
        "h1": "Garten, Treibhaus für deinen Event in der Schweiz",
        "results_count": "41 Resultate"
    },
    {
        "url": "https://www.eventlokale.ch/locations/freizeitanlage",
        "h1": "Freizeitanlage für deinen Event in der Schweiz",
        "results_count": "132 Resultate"
    },
    {
        "url": "https://www.eventlokale.ch/locations/galerie_atelier",
        "h1": "Galerie, Atelier für deinen Event in der Schweiz",
        "results_count": "34 Resultate"
    },
    {
        "url": "https://www.eventlokale.ch/locations/hangar_werft",
        "h1": "Hangar, Werft für deinen Event in der Schweiz",
        "results_count": "4 Resultate"
    },
    {
        "url": "https://www.eventlokale.ch/locations/kino",
        "h1": "Kino für deinen Event in der Schweiz",
        "results_count": "24 Resultate"
    },
    {
        "url": "https://www.eventlokale.ch/locations/kulturzentrum",
        "h1": "Kulturzentrum für deinen Event in der Schweiz",
        "results_count": "108 Resultate"
    },
    {
        "url": "https://www.eventlokale.ch/locations/museum",
        "h1": "Museum für deinen Event in der Schweiz",
        "results_count": "86 Resultate"
    },
    {
        "url": "https://www.eventlokale.ch/locations/schiff",
        "h1": "Schiff für deinen Event in der Schweiz",
        "results_count": "26 Resultate"
    },
    {
        "url": "https://www.eventlokale.ch/locations/openair_outdoor",
        "h1": "Openair, Outdoor für deinen Event in der Schweiz",
        "results_count": "74 Resultate"
    },
    {
        "url": "https://www.eventlokale.ch/locations/theater",
        "h1": "Theater für deinen Event in der Schweiz",
        "results_count": "66 Resultate"
    },
    {
        "url": "https://www.eventlokale.ch/locations/tram_bahn_bus",
        "h1": "Tram, Bahn, Bus für deinen Event in der Schweiz",
        "results_count": "8 Resultate"
    },
    {
        "url": "https://www.eventlokale.ch/locations/villa",
        "h1": "Villa für deinen Event in der Schweiz",
        "results_count": "38 Resultate"
    },
    {
        "url": "https://www.eventlokale.ch/locations/zelt_zirkuszelt",
        "h1": "Zelt, Zirkuszelt für deinen Event in der Schweiz",
        "results_count": "23 Resultate"
    },
    {
        "url": "https://www.eventlokale.ch/locations/zunfthaus",
        "h1": "Zunfthaus für deinen Event in der Schweiz",
        "results_count": "10 Resultate"
    },
    {
        "url": "https://www.eventlokale.ch/locations/historische_staette",
        "h1": "Historische Stätte für deinen Event in der Schweiz",
        "results_count": "112 Resultate"
    },
    {
        "url": "https://www.eventlokale.ch/locations/seminarraum",
        "h1": "Seminarraum für deinen Event in der Schweiz",
        "results_count": "481 Resultate"
    },
    {
        "url": "https://www.eventlokale.ch/locations/sitzungszimmer",
        "h1": "Sitzungszimmer für deinen Event in der Schweiz",
        "results_count": "293 Resultate"
    },
    {
        "url": "https://www.eventlokale.ch/locations/digitale_location",
        "h1": "Digitale Location für deinen Event in der Schweiz",
        "results_count": "45 Resultate"
    },
    {
        "url": "https://www.eventlokale.ch/locations/thurgau",
        "h1": "Locations für deinen Event im Kanton Thurgau",
        "results_count": "156 Resultate"
    }
]