[
    {
        "url": "https://www.eventlokale.ch/locations/theater/standort=Biel",
        "h1": "Theater für deinen Event in Biel",
        "results_count": "0 Resultat"
    },
    {
        "url": "https://www.eventlokale.ch/locations/theater/standort=Luzern",
        "h1": "Theater für deinen Event in Luzern",
        "results_count": "1 Resultat"
    },
    {
        "url": "https://www.eventlokale.ch/locations/theater/standort=St.%20Gallen",
        "h1": "Theater für deinen Event in St. Gallen",
        "results_count": "0 Resultat"
    },
    {
        "url": "https://www.eventlokale.ch/locations/theater/standort=Thun",
        "h1": "Theater für deinen Event in Thun",
        "results_count": "2 Resultate"
    },
    {
        "url": "https://www.eventlokale.ch/locations/theater/standort=Lugano",
        "h1": "Theater für deinen Event in Lugano",
        "results_count": "0 Resultat"
    },
    {
        "url": "https://www.eventlokale.ch/locations/theater/standort=K%C3%B6niz",
        "h1": "Theater für deinen Event in Köniz",
        "results_count": "0 Resultat"
    },
    {
        "url": "https://www.eventlokale.ch/locations/theater/standort=Chur",
        "h1": "Theater für deinen Event in Chur",
        "results_count": "0 Resultat"
    },
    {
        "url": "https://www.eventlokale.ch/locations/theater/standort=Freiburg",
        "h1": "Theater für deinen Event in Freiburg",
        "results_count": "0 Resultat"
    },
    {
        "url": "https://www.eventlokale.ch/locations/theater/standort=Schaffhausen",
        "h1": "Theater für deinen Event in Schaffhausen",
        "results_count": "0 Resultat"
    },
    {
        "url": "https://www.eventlokale.ch/locations/theater/standort=La%20Chaux-de-Fonds",
        "h1": "Theater für deinen Event in La Chaux-de-Fonds",
        "results_count": "0 Resultat"
    },
    {
        "url": "https://www.eventlokale.ch/locations/theater/standort=Vernier",
        "h1": "Theater für deinen Event in Vernier",
        "results_count": "0 Resultat"
    },
    {
        "url": "https://www.eventlokale.ch/locations/theater/standort=Uster",
        "h1": "Theater für deinen Event in Uster",
        "results_count": "0 Resultat"
    },
    {
        "url": "https://www.eventlokale.ch/locations/theater/standort=Sitten",
        "h1": "Theater für deinen Event in Sitten",
        "results_count": "0 Resultat"
    },
    {
        "url": "https://www.eventlokale.ch/locations/theater/standort=Neuenburg",
        "h1": "Theater für deinen Event in Neuenburg",
        "results_count": "0 Resultat"
    },
    {
        "url": "https://www.eventlokale.ch/locations/theater/standort=Lancy",
        "h1": "Theater für deinen Event in Lancy",
        "results_count": "0 Resultat"
    },
    {
        "url": "https://www.eventlokale.ch/locations/theater/standort=Yverdon-les-Bains",
        "h1": "Theater für deinen Event in Yverdon-les-Bains",
        "results_count": "0 Resultat"
    },
    {
        "url": "https://www.eventlokale.ch/locations/theater/standort=Zug",
        "h1": "Theater für deinen Event in Zug",
        "results_count": "0 Resultat"
    },
    {
        "url": "https://www.eventlokale.ch/locations/theater/standort=Kriens",
        "h1": "Theater für deinen Event in Kriens",
        "results_count": "0 Resultat"
    },
    {
        "url": "https://www.eventlokale.ch/locations/theater/standort=Emmen",
        "h1": "Theater für deinen Event in Emmen",
        "results_count": "0 Resultat"
    },
    {
        "url": "https://www.eventlokale.ch/locations/theater/standort=Rapperswil-Jona",
        "h1": "Theater für deinen Event in Rapperswil-Jona",
        "results_count": "0 Resultat"
    },
    {
        "url": "https://www.eventlokale.ch/locations/theater/standort=D%C3%BCbendorf",
        "h1": "Theater für deinen Event in Dübendorf",
        "results_count": "0 Resultat"
    },
    {
        "url": "https://www.eventlokale.ch/locations/theater/standort=Montreux",
        "h1": "Theater für deinen Event in Montreux",
        "results_count": "0 Resultat"
    },
    {
        "url": "https://www.eventlokale.ch/locations/theater/standort=Dietikon",
        "h1": "Theater für deinen Event in Dietikon",
        "results_count": "1 Resultat"
    },
    {
        "url": "https://www.eventlokale.ch/locations/theater/standort=Wetzikon",
        "h1": "Theater für deinen Event in Wetzikon",
        "results_count": "0 Resultat"
    },
    {
        "url": "https://www.eventlokale.ch/locations/theater/standort=Frauenfeld",
        "h1": "Theater für deinen Event in Frauenfeld",
        "results_count": "1 Resultat"
    },
    {
        "url": "https://www.eventlokale.ch/locations/theater/standort=Wil",
        "h1": "Theater für deinen Event in Wil",
        "results_count": "0 Resultat"
    },
    {
        "url": "https://www.eventlokale.ch/locations/theater/standort=Baar",
        "h1": "Theater für deinen Event in Baar",
        "results_count": "0 Resultat"
    },
    {
        "url": "https://www.eventlokale.ch/locations/theater/standort=Bulle",
        "h1": "Theater für deinen Event in Bulle",
        "results_count": "0 Resultat"
    },
    {
        "url": "https://www.eventlokale.ch/locations/theater/standort=Meyrin",
        "h1": "Theater für deinen Event in Meyrin",
        "results_count": "0 Resultat"
    },
    {
        "url": "https://www.eventlokale.ch/locations/theater/standort=W%C3%A4denswil",
        "h1": "Theater für deinen Event in Wädenswil",
        "results_count": "0 Resultat"
    },
    {
        "url": "https://www.eventlokale.ch/locations/theater/standort=Kreuzlingen",
        "h1": "Theater für deinen Event in Kreuzlingen",
        "results_count": "0 Resultat"
    },
    {
        "url": "https://www.eventlokale.ch/locations/theater/standort=Carouge",
        "h1": "Theater für deinen Event in Carouge",
        "results_count": "0 Resultat"
    },
    {
        "url": "https://www.eventlokale.ch/locations/theater/standort=Riehen",
        "h1": "Theater für deinen Event in Riehen",
        "results_count": "0 Resultat"
    },
    {
        "url": "https://www.eventlokale.ch/locations/theater/standort=Renens",
        "h1": "Theater für deinen Event in Renens",
        "results_count": "0 Resultat"
    },
    {
        "url": "https://www.eventlokale.ch/locations/theater/standort=Aarau",
        "h1": "Theater für deinen Event in Aarau",
        "results_count": "0 Resultat"
    },
    {
        "url": "https://www.eventlokale.ch/locations/theater/standort=Allschwil",
        "h1": "Theater für deinen Event in Allschwil",
        "results_count": "0 Resultat"
    },
    {
        "url": "https://www.eventlokale.ch/locations/theater/standort=Wettingen",
        "h1": "Theater für deinen Event in Wettingen",
        "results_count": "0 Resultat"
    },
    {
        "url": "https://www.eventlokale.ch/locations/theater/standort=Horgen",
        "h1": "Theater für deinen Event in Horgen",
        "results_count": "0 Resultat"
    },
    {
        "url": "https://www.eventlokale.ch/locations/theater/standort=Nyon",
        "h1": "Theater für deinen Event in Nyon",
        "results_count": "0 Resultat"
    },
    {
        "url": "https://www.eventlokale.ch/locations/theater/standort=Vevey",
        "h1": "Theater für deinen Event in Vevey",
        "results_count": "0 Resultat"
    },
    {
        "url": "https://www.eventlokale.ch/locations/theater/standort=B%C3%BClach",
        "h1": "Theater für deinen Event in Bülach",
        "results_count": "0 Resultat"
    },
    {
        "url": "https://www.eventlokale.ch/locations/theater/standort=Reinach",
        "h1": "Theater für deinen Event in Reinach",
        "results_count": "0 Resultat"
    },
    {
        "url": "https://www.eventlokale.ch/locations/theater/standort=Volketswil",
        "h1": "Theater für deinen Event in Volketswil",
        "results_count": "0 Resultat"
    },
    {
        "url": "https://www.eventlokale.ch/locations/theater/standort=Adliswil",
        "h1": "Theater für deinen Event in Adliswil",
        "results_count": "1 Resultat"
    },
    {
        "url": "https://www.eventlokale.ch/locations/theater/standort=Baden",
        "h1": "Theater für deinen Event in Baden",
        "results_count": "1 Resultat"
    },
    {
        "url": "https://www.eventlokale.ch/locations/theater/standort=Kloten",
        "h1": "Theater für deinen Event in Kloten",
        "results_count": "0 Resultat"
    },
    {
        "url": "https://www.eventlokale.ch/locations/theater/standort=Onex",
        "h1": "Theater für deinen Event in Onex",
        "results_count": "0 Resultat"
    },
    {
        "url": "https://www.eventlokale.ch/locations/theater/standort=Bellinzona",
        "h1": "Theater für deinen Event in Bellinzona",
        "results_count": "1 Resultat"
    },
    {
        "url": "https://www.eventlokale.ch/locations/theater/standort=Gossau",
        "h1": "Theater für deinen Event in Gossau",
        "results_count": "0 Resultat"
    },
    {
        "url": "https://www.eventlokale.ch/locations/theater/standort=Thalwil",
        "h1": "Theater für deinen Event in Thalwil",
        "results_count": "1 Resultat"
    },
    {
        "url": "https://www.eventlokale.ch/locations/theater/standort=Pully",
        "h1": "Theater für deinen Event in Pully",
        "results_count": "0 Resultat"
    },
    {
        "url": "https://www.eventlokale.ch/locations/theater/standort=Schlieren",
        "h1": "Theater für deinen Event in Schlieren",
        "results_count": "0 Resultat"
    },
    {
        "url": "https://www.eventlokale.ch/locations/theater/standort=Glarus%20Nord",
        "h1": "Theater für deinen Event in Glarus Nord",
        "results_count": "0 Resultat"
    },
    {
        "url": "https://www.eventlokale.ch/locations/theater/standort=Muttenz",
        "h1": "Theater für deinen Event in Muttenz",
        "results_count": "0 Resultat"
    },
    {
        "url": "https://www.eventlokale.ch/locations/theater/standort=Regensdorf",
        "h1": "Theater für deinen Event in Regensdorf",
        "results_count": "0 Resultat"
    },
    {
        "url": "https://www.eventlokale.ch/locations/theater/standort=Monthey",
        "h1": "Theater für deinen Event in Monthey",
        "results_count": "0 Resultat"
    },
    {
        "url": "https://www.eventlokale.ch/locations/theater/standort=Olten",
        "h1": "Theater für deinen Event in Olten",
        "results_count": "1 Resultat"
    },
    {
        "url": "https://www.eventlokale.ch/locations/theater/standort=Opfikon",
        "h1": "Theater für deinen Event in Opfikon",
        "results_count": "0 Resultat"
    },
    {
        "url": "https://www.eventlokale.ch/locations/theater/standort=Martigny",
        "h1": "Theater für deinen Event in Martigny",
        "results_count": "0 Resultat"
    },
    {
        "url": "https://www.eventlokale.ch/locations/theater/standort=Siders",
        "h1": "Theater für deinen Event in Siders",
        "results_count": "0 Resultat"
    },
    {
        "url": "https://www.eventlokale.ch/locations/theater/standort=Ostermundigen",
        "h1": "Theater für deinen Event in Ostermundigen",
        "results_count": "0 Resultat"
    },
    {
        "url": "https://www.eventlokale.ch/locations/theater/standort=Solothurn",
        "h1": "Theater für deinen Event in Solothurn",
        "results_count": "2 Resultate"
    },
    {
        "url": "https://www.eventlokale.ch/locations/theater/standort=Grenchen",
        "h1": "Theater für deinen Event in Grenchen",
        "results_count": "1 Resultat"
    },
    {
        "url": "https://www.eventlokale.ch/locations/theater/standort=Illnau-Effretikon",
        "h1": "Theater für deinen Event in Illnau-Effretikon",
        "results_count": "0 Resultat"
    },
    {
        "url": "https://www.eventlokale.ch/locations/theater/standort=Burgdorf",
        "h1": "Theater für deinen Event in Burgdorf",
        "results_count": "0 Resultat"
    },
    {
        "url": "https://www.eventlokale.ch/locations/theater/standort=Freienbach",
        "h1": "Theater für deinen Event in Freienbach",
        "results_count": "0 Resultat"
    },
    {
        "url": "https://www.eventlokale.ch/locations/theater/standort=Steffisburg",
        "h1": "Theater für deinen Event in Steffisburg",
        "results_count": "0 Resultat"
    },
    {
        "url": "https://www.eventlokale.ch/locations/theater/standort=Locarno",
        "h1": "Theater für deinen Event in Locarno",
        "results_count": "1 Resultat"
    },
    {
        "url": "https://www.eventlokale.ch/locations/theater/standort=Pratteln",
        "h1": "Theater für deinen Event in Pratteln",
        "results_count": "0 Resultat"
    },
    {
        "url": "https://www.eventlokale.ch/locations/theater/standort=Cham",
        "h1": "Theater für deinen Event in Cham",
        "results_count": "0 Resultat"
    },
    {
        "url": "https://www.eventlokale.ch/locations/theater/standort=Morges",
        "h1": "Theater für deinen Event in Morges",
        "results_count": "1 Resultat"
    },
    {
        "url": "https://www.eventlokale.ch/locations/theater/standort=Herisau",
        "h1": "Theater für deinen Event in Herisau",
        "results_count": "0 Resultat"
    },
    {
        "url": "https://www.eventlokale.ch/locations/theater/standort=Wohlen",
        "h1": "Theater für deinen Event in Wohlen",
        "results_count": "0 Resultat"
    },
    {
        "url": "https://www.eventlokale.ch/locations/theater/standort=Wallisellen",
        "h1": "Theater für deinen Event in Wallisellen",
        "results_count": "0 Resultat"
    },
    {
        "url": "https://www.eventlokale.ch/locations/theater/standort=Langenthal",
        "h1": "Theater für deinen Event in Langenthal",
        "results_count": "1 Resultat"
    },
    {
        "url": "https://www.eventlokale.ch/locations/theater/standort=Einsiedeln",
        "h1": "Theater für deinen Event in Einsiedeln",
        "results_count": "0 Resultat"
    },
    {
        "url": "https://www.eventlokale.ch/locations/theater/standort=Mendrisio",
        "h1": "Theater für deinen Event in Mendrisio",
        "results_count": "0 Resultat"
    },
    {
        "url": "https://www.eventlokale.ch/locations/theater/standort=Schwyz",
        "h1": "Theater für deinen Event in Schwyz",
        "results_count": "0 Resultat"
    },
    {
        "url": "https://www.eventlokale.ch/locations/theater/standort=Lyss",
        "h1": "Theater für deinen Event in Lyss",
        "results_count": "0 Resultat"
    },
    {
        "url": "https://www.eventlokale.ch/locations/theater/standort=Arbon",
        "h1": "Theater für deinen Event in Arbon",
        "results_count": "0 Resultat"
    },
    {
        "url": "https://www.eventlokale.ch/locations/theater/standort=Th%C3%B4nex",
        "h1": "Theater für deinen Event in Thônex",
        "results_count": "0 Resultat"
    },
    {
        "url": "https://www.eventlokale.ch/locations/theater/standort=Liestal",
        "h1": "Theater für deinen Event in Liestal",
        "results_count": "0 Resultat"
    },
    {
        "url": "https://www.eventlokale.ch/locations/theater/standort=St%C3%A4fa",
        "h1": "Theater für deinen Event in Stäfa",
        "results_count": "0 Resultat"
    },
    {
        "url": "https://www.eventlokale.ch/locations/theater/standort=K%C3%BCsnacht",
        "h1": "Theater für deinen Event in Küsnacht",
        "results_count": "0 Resultat"
    },
    {
        "url": "https://www.eventlokale.ch/locations/theater/standort=Horw",
        "h1": "Theater für deinen Event in Horw",
        "results_count": "0 Resultat"
    },
    {
        "url": "https://www.eventlokale.ch/locations/theater/standort=Meilen",
        "h1": "Theater für deinen Event in Meilen",
        "results_count": "0 Resultat"
    },
    {
        "url": "https://www.eventlokale.ch/locations/theater/standort=Oftringen",
        "h1": "Theater für deinen Event in Oftringen",
        "results_count": "0 Resultat"
    },
    {
        "url": "https://www.eventlokale.ch/locations/theater/standort=Versoix",
        "h1": "Theater für deinen Event in Versoix",
        "results_count": "0 Resultat"
    },
    {
        "url": "https://www.eventlokale.ch/locations/theater/standort=Muri%20bei%20Bern",
        "h1": "Theater für deinen Event in Muri bei Bern",
        "results_count": "0 Resultat"
    },
    {
        "url": "https://www.eventlokale.ch/locations/theater/standort=Richterswil",
        "h1": "Theater für deinen Event in Richterswil",
        "results_count": "0 Resultat"
    },
    {
        "url": "https://www.eventlokale.ch/locations/theater/standort=Rheinfelden",
        "h1": "Theater für deinen Event in Rheinfelden",
        "results_count": "0 Resultat"
    },
    {
        "url": "https://www.eventlokale.ch/locations/theater/standort=Amriswil",
        "h1": "Theater für deinen Event in Amriswil",
        "results_count": "0 Resultat"
    },
    {
        "url": "https://www.eventlokale.ch/locations/theater/standort=Ebikon",
        "h1": "Theater für deinen Event in Ebikon",
        "results_count": "0 Resultat"
    },
    {
        "url": "https://www.eventlokale.ch/locations/theater/standort=Gland",
        "h1": "Theater für deinen Event in Gland",
        "results_count": "0 Resultat"
    },
    {
        "url": "https://www.eventlokale.ch/locations/theater/standort=Spiez",
        "h1": "Theater für deinen Event in Spiez",
        "results_count": "0 Resultat"
    }
]