[
    {
        "url": "https://www.eventlokale.ch/locations/waldhuette/hochzeit",
        "h1": "Waldhütte für Hochzeit in der Schweiz",
        "results_count": "3 Resultate"
    },
    {
        "url": "https://www.eventlokale.ch/locations/waldhuette/teamevent",
        "h1": "Waldhütte für Teamevent in der Schweiz",
        "results_count": "9 Resultate"
    },
    {
        "url": "https://www.eventlokale.ch/locations/waldhuette/geburtstag",
        "h1": "Waldhütte für Geburtstag in der Schweiz",
        "results_count": "27 Resultate"
    },
    {
        "url": "https://www.eventlokale.ch/locations/waldhuette/privatanlass",
        "h1": "Waldhütte für Privatanlass in der Schweiz",
        "results_count": "16 Resultate"
    },
    {
        "url": "https://www.eventlokale.ch/locations/waldhuette/familienfeier",
        "h1": "Waldhütte für Familienfeier in der Schweiz",
        "results_count": "26 Resultate"
    },
    {
        "url": "https://www.eventlokale.ch/locations/waldhuette/apero",
        "h1": "Waldhütte für Apéro in der Schweiz",
        "results_count": "2 Resultate"
    },
    {
        "url": "https://www.eventlokale.ch/locations/waldhuette/party",
        "h1": "Waldhütte für Party, Feier in der Schweiz",
        "results_count": "14 Resultate"
    },
    {
        "url": "https://www.eventlokale.ch/locations/waldhuette/theater-1",
        "h1": "Waldhütte für Theater in der Schweiz",
        "results_count": "0 Resultat"
    },
    {
        "url": "https://www.eventlokale.ch/locations/waldhuette/konzert",
        "h1": "Waldhütte für Konzert in der Schweiz",
        "results_count": "0 Resultat"
    },
    {
        "url": "https://www.eventlokale.ch/locations/waldhuette/messe_ausstellung",
        "h1": "Waldhütte für Messe, Ausstellung in der Schweiz",
        "results_count": "0 Resultat"
    },
    {
        "url": "https://www.eventlokale.ch/locations/waldhuette/weihnachtsfeier",
        "h1": "Waldhütte für Weihnachtsfeier in der Schweiz",
        "results_count": "4 Resultate"
    },
    {
        "url": "https://www.eventlokale.ch/locations/waldhuette/klassentreffen",
        "h1": "Waldhütte für Klassentreffen in der Schweiz",
        "results_count": "132 Resultate"
    },
    {
        "url": "https://www.eventlokale.ch/locations/waldhuette/sportanlass",
        "h1": "Waldhütte für Sportanlass in der Schweiz",
        "results_count": "2 Resultate"
    },
    {
        "url": "https://www.eventlokale.ch/locations/waldhuette/oeffentlicher_anlass",
        "h1": "Waldhütte für Öffentlicher Anlass in der Schweiz",
        "results_count": "0 Resultat"
    },
    {
        "url": "https://www.eventlokale.ch/locations/waldhuette/party-1",
        "h1": "Waldhütte für Party in der Schweiz",
        "results_count": "0 Resultat"
    },
    {
        "url": "https://www.eventlokale.ch/locations/bauernhof_scheune/vereinsanlass",
        "h1": "Bauernhof, Scheune für Vereinsanlass in der Schweiz",
        "results_count": "19 Resultate"
    },
    {
        "url": "https://www.eventlokale.ch/locations/bauernhof_scheune/kongress",
        "h1": "Bauernhof, Scheune für Kongress in der Schweiz",
        "results_count": "1 Resultat"
    },
    {
        "url": "https://www.eventlokale.ch/locations/bauernhof_scheune/firmenanlass",
        "h1": "Bauernhof, Scheune für Firmenanlass in der Schweiz",
        "results_count": "44 Resultate"
    },
    {
        "url": "https://www.eventlokale.ch/locations/bauernhof_scheune/gv_versammlung",
        "h1": "Bauernhof, Scheune für Versammlung, GV in der Schweiz",
        "results_count": "7 Resultate"
    },
    {
        "url": "https://www.eventlokale.ch/locations/bauernhof_scheune/geburtstag",
        "h1": "Bauernhof, Scheune für Geburtstag in der Schweiz",
        "results_count": "54 Resultate"
    },
    {
        "url": "https://www.eventlokale.ch/locations/bauernhof_scheune/meeting",
        "h1": "Bauernhof, Scheune für Meeting in der Schweiz",
        "results_count": "8 Resultate"
    },
    {
        "url": "https://www.eventlokale.ch/locations/bauernhof_scheune/tagung",
        "h1": "Bauernhof, Scheune für Tagung in der Schweiz",
        "results_count": "4 Resultate"
    },
    {
        "url": "https://www.eventlokale.ch/locations/bauernhof_scheune/hochzeit",
        "h1": "Bauernhof, Scheune für Hochzeit in der Schweiz",
        "results_count": "44 Resultate"
    },
    {
        "url": "https://www.eventlokale.ch/locations/bauernhof_scheune/familienfeier",
        "h1": "Bauernhof, Scheune für Familienfeier in der Schweiz",
        "results_count": "46 Resultate"
    },
    {
        "url": "https://www.eventlokale.ch/locations/bauernhof_scheune/privatanlass",
        "h1": "Bauernhof, Scheune für Privatanlass in der Schweiz",
        "results_count": "25 Resultate"
    },
    {
        "url": "https://www.eventlokale.ch/locations/bauernhof_scheune/apero",
        "h1": "Bauernhof, Scheune für Apéro in der Schweiz",
        "results_count": "19 Resultate"
    },
    {
        "url": "https://www.eventlokale.ch/locations/bauernhof_scheune/party",
        "h1": "Bauernhof, Scheune für Party, Feier in der Schweiz",
        "results_count": "9 Resultate"
    },
    {
        "url": "https://www.eventlokale.ch/locations/bauernhof_scheune/teamevent",
        "h1": "Bauernhof, Scheune für Teamevent in der Schweiz",
        "results_count": "24 Resultate"
    },
    {
        "url": "https://www.eventlokale.ch/locations/bauernhof_scheune/konzert",
        "h1": "Bauernhof, Scheune für Konzert in der Schweiz",
        "results_count": "2 Resultate"
    },
    {
        "url": "https://www.eventlokale.ch/locations/bauernhof_scheune/theater-1",
        "h1": "Bauernhof, Scheune für Theater in der Schweiz",
        "results_count": "1 Resultat"
    },
    {
        "url": "https://www.eventlokale.ch/locations/bauernhof_scheune/messe_ausstellung",
        "h1": "Bauernhof, Scheune für Messe, Ausstellung in der Schweiz",
        "results_count": "0 Resultat"
    },
    {
        "url": "https://www.eventlokale.ch/locations/bauernhof_scheune/klassentreffen",
        "h1": "Bauernhof, Scheune für Klassentreffen in der Schweiz",
        "results_count": "4 Resultate"
    },
    {
        "url": "https://www.eventlokale.ch/locations/bauernhof_scheune/weihnachtsfeier",
        "h1": "Bauernhof, Scheune für Weihnachtsfeier in der Schweiz",
        "results_count": "12 Resultate"
    },
    {
        "url": "https://www.eventlokale.ch/locations/bauernhof_scheune/party-1",
        "h1": "Bauernhof, Scheune für Party in der Schweiz",
        "results_count": "2 Resultate"
    },
    {
        "url": "https://www.eventlokale.ch/locations/bauernhof_scheune/sportanlass",
        "h1": "Bauernhof, Scheune für Sportanlass in der Schweiz",
        "results_count": "1 Resultat"
    },
    {
        "url": "https://www.eventlokale.ch/locations/bauernhof_scheune/oeffentlicher_anlass",
        "h1": "Bauernhof, Scheune für Öffentlicher Anlass in der Schweiz",
        "results_count": "2 Resultate"
    },
    {
        "url": "https://www.eventlokale.ch/locations/berghuette_alphuette/vereinsanlass",
        "h1": "Berghütte, Alphütte für Vereinsanlass in der Schweiz",
        "results_count": "13 Resultate"
    },
    {
        "url": "https://www.eventlokale.ch/locations/berghuette_alphuette/kongress",
        "h1": "Berghütte, Alphütte für Kongress in der Schweiz",
        "results_count": "0 Resultat"
    },
    {
        "url": "https://www.eventlokale.ch/locations/berghuette_alphuette/firmenanlass",
        "h1": "Berghütte, Alphütte für Firmenanlass in der Schweiz",
        "results_count": "41 Resultate"
    },
    {
        "url": "https://www.eventlokale.ch/locations/berghuette_alphuette/gv_versammlung",
        "h1": "Berghütte, Alphütte für Versammlung, GV in der Schweiz",
        "results_count": "4 Resultate"
    },
    {
        "url": "https://www.eventlokale.ch/locations/berghuette_alphuette/meeting",
        "h1": "Berghütte, Alphütte für Meeting in der Schweiz",
        "results_count": "9 Resultate"
    },
    {
        "url": "https://www.eventlokale.ch/locations/berghuette_alphuette/tagung",
        "h1": "Berghütte, Alphütte für Tagung in der Schweiz",
        "results_count": "6 Resultate"
    },
    {
        "url": "https://www.eventlokale.ch/locations/berghuette_alphuette/geburtstag",
        "h1": "Berghütte, Alphütte für Geburtstag in der Schweiz",
        "results_count": "41 Resultate"
    },
    {
        "url": "https://www.eventlokale.ch/locations/berghuette_alphuette/hochzeit",
        "h1": "Berghütte, Alphütte für Hochzeit in der Schweiz",
        "results_count": "23 Resultate"
    },
    {
        "url": "https://www.eventlokale.ch/locations/berghuette_alphuette/familienfeier",
        "h1": "Berghütte, Alphütte für Familienfeier in der Schweiz",
        "results_count": "45 Resultate"
    },
    {
        "url": "https://www.eventlokale.ch/locations/berghuette_alphuette/privatanlass",
        "h1": "Berghütte, Alphütte für Privatanlass in der Schweiz",
        "results_count": "41 Resultate"
    },
    {
        "url": "https://www.eventlokale.ch/locations/berghuette_alphuette/apero",
        "h1": "Berghütte, Alphütte für Apéro in der Schweiz",
        "results_count": "20 Resultate"
    },
    {
        "url": "https://www.eventlokale.ch/locations/berghuette_alphuette/teamevent",
        "h1": "Berghütte, Alphütte für Teamevent in der Schweiz",
        "results_count": "37 Resultate"
    },
    {
        "url": "https://www.eventlokale.ch/locations/berghuette_alphuette/party",
        "h1": "Berghütte, Alphütte für Party, Feier in der Schweiz",
        "results_count": "10 Resultate"
    },
    {
        "url": "https://www.eventlokale.ch/locations/berghuette_alphuette/konzert",
        "h1": "Berghütte, Alphütte für Konzert in der Schweiz",
        "results_count": "0 Resultat"
    },
    {
        "url": "https://www.eventlokale.ch/locations/berghuette_alphuette/theater-1",
        "h1": "Berghütte, Alphütte für Theater in der Schweiz",
        "results_count": "0 Resultat"
    },
    {
        "url": "https://www.eventlokale.ch/locations/berghuette_alphuette/messe_ausstellung",
        "h1": "Berghütte, Alphütte für Messe, Ausstellung in der Schweiz",
        "results_count": "0 Resultat"
    },
    {
        "url": "https://www.eventlokale.ch/locations/berghuette_alphuette/weihnachtsfeier",
        "h1": "Berghütte, Alphütte für Weihnachtsfeier in der Schweiz",
        "results_count": "13 Resultate"
    },
    {
        "url": "https://www.eventlokale.ch/locations/berghuette_alphuette/party-1",
        "h1": "Berghütte, Alphütte für Party in der Schweiz",
        "results_count": "0 Resultat"
    },
    {
        "url": "https://www.eventlokale.ch/locations/berghuette_alphuette/klassentreffen",
        "h1": "Berghütte, Alphütte für Klassentreffen in der Schweiz",
        "results_count": "9 Resultate"
    },
    {
        "url": "https://www.eventlokale.ch/locations/berghuette_alphuette/sportanlass",
        "h1": "Berghütte, Alphütte für Sportanlass in der Schweiz",
        "results_count": "3 Resultate"
    },
    {
        "url": "https://www.eventlokale.ch/locations/berghuette_alphuette/oeffentlicher_anlass",
        "h1": "Berghütte, Alphütte für Öffentlicher Anlass in der Schweiz",
        "results_count": "2 Resultate"
    },
    {
        "url": "https://www.eventlokale.ch/locations/brauerei_weingut/vereinsanlass",
        "h1": "Brauerei, Weingut für Vereinsanlass in der Schweiz",
        "results_count": "3 Resultate"
    },
    {
        "url": "https://www.eventlokale.ch/locations/brauerei_weingut/firmenanlass",
        "h1": "Brauerei, Weingut für Firmenanlass in der Schweiz",
        "results_count": "29 Resultate"
    },
    {
        "url": "https://www.eventlokale.ch/locations/brauerei_weingut/gv_versammlung",
        "h1": "Brauerei, Weingut für Versammlung, GV in der Schweiz",
        "results_count": "2 Resultate"
    },
    {
        "url": "https://www.eventlokale.ch/locations/brauerei_weingut/kongress",
        "h1": "Brauerei, Weingut für Kongress in der Schweiz",
        "results_count": "0 Resultat"
    },
    {
        "url": "https://www.eventlokale.ch/locations/brauerei_weingut/meeting",
        "h1": "Brauerei, Weingut für Meeting in der Schweiz",
        "results_count": "5 Resultate"
    },
    {
        "url": "https://www.eventlokale.ch/locations/brauerei_weingut/tagung",
        "h1": "Brauerei, Weingut für Tagung in der Schweiz",
        "results_count": "8 Resultate"
    },
    {
        "url": "https://www.eventlokale.ch/locations/brauerei_weingut/geburtstag",
        "h1": "Brauerei, Weingut für Geburtstag in der Schweiz",
        "results_count": "21 Resultate"
    },
    {
        "url": "https://www.eventlokale.ch/locations/brauerei_weingut/hochzeit",
        "h1": "Brauerei, Weingut für Hochzeit in der Schweiz",
        "results_count": "22 Resultate"
    },
    {
        "url": "https://www.eventlokale.ch/locations/brauerei_weingut/familienfeier",
        "h1": "Brauerei, Weingut für Familienfeier in der Schweiz",
        "results_count": "19 Resultate"
    },
    {
        "url": "https://www.eventlokale.ch/locations/brauerei_weingut/privatanlass",
        "h1": "Brauerei, Weingut für Privatanlass in der Schweiz",
        "results_count": "32 Resultate"
    },
    {
        "url": "https://www.eventlokale.ch/locations/brauerei_weingut/teamevent",
        "h1": "Brauerei, Weingut für Teamevent in der Schweiz",
        "results_count": "30 Resultate"
    },
    {
        "url": "https://www.eventlokale.ch/locations/brauerei_weingut/apero",
        "h1": "Brauerei, Weingut für Apéro in der Schweiz",
        "results_count": "24 Resultate"
    },
    {
        "url": "https://www.eventlokale.ch/locations/brauerei_weingut/party",
        "h1": "Brauerei, Weingut für Party, Feier in der Schweiz",
        "results_count": "8 Resultate"
    },
    {
        "url": "https://www.eventlokale.ch/locations/brauerei_weingut/konzert",
        "h1": "Brauerei, Weingut für Konzert in der Schweiz",
        "results_count": "0 Resultat"
    },
    {
        "url": "https://www.eventlokale.ch/locations/brauerei_weingut/theater-1",
        "h1": "Brauerei, Weingut für Theater in der Schweiz",
        "results_count": "0 Resultat"
    },
    {
        "url": "https://www.eventlokale.ch/locations/brauerei_weingut/messe_ausstellung",
        "h1": "Brauerei, Weingut für Messe, Ausstellung in der Schweiz",
        "results_count": "0 Resultat"
    },
    {
        "url": "https://www.eventlokale.ch/locations/brauerei_weingut/weihnachtsfeier",
        "h1": "Brauerei, Weingut für Weihnachtsfeier in der Schweiz",
        "results_count": "4 Resultate"
    },
    {
        "url": "https://www.eventlokale.ch/locations/brauerei_weingut/party-1",
        "h1": "Brauerei, Weingut für Party in der Schweiz",
        "results_count": "1 Resultat"
    },
    {
        "url": "https://www.eventlokale.ch/locations/brauerei_weingut/klassentreffen",
        "h1": "Brauerei, Weingut für Klassentreffen in der Schweiz",
        "results_count": "6 Resultate"
    },
    {
        "url": "https://www.eventlokale.ch/locations/brauerei_weingut/sportanlass",
        "h1": "Brauerei, Weingut für Sportanlass in der Schweiz",
        "results_count": "0 Resultat"
    },
    {
        "url": "https://www.eventlokale.ch/locations/brauerei_weingut/oeffentlicher_anlass",
        "h1": "Brauerei, Weingut für Öffentlicher Anlass in der Schweiz",
        "results_count": "1 Resultat"
    },
    {
        "url": "https://www.eventlokale.ch/locations/burg/vereinsanlass",
        "h1": "Burg für Vereinsanlass in der Schweiz",
        "results_count": "0 Resultat"
    },
    {
        "url": "https://www.eventlokale.ch/locations/burg/kongress",
        "h1": "Burg für Kongress in der Schweiz",
        "results_count": "1 Resultat"
    },
    {
        "url": "https://www.eventlokale.ch/locations/burg/firmenanlass",
        "h1": "Burg für Firmenanlass in der Schweiz",
        "results_count": "5 Resultate"
    },
    {
        "url": "https://www.eventlokale.ch/locations/burg/gv_versammlung",
        "h1": "Burg für Versammlung, GV in der Schweiz",
        "results_count": "0 Resultat"
    },
    {
        "url": "https://www.eventlokale.ch/locations/burg/geburtstag",
        "h1": "Burg für Geburtstag in der Schweiz",
        "results_count": "8 Resultate"
    },
    {
        "url": "https://www.eventlokale.ch/locations/burg/tagung",
        "h1": "Burg für Tagung in der Schweiz",
        "results_count": "1 Resultat"
    },
    {
        "url": "https://www.eventlokale.ch/locations/burg/meeting",
        "h1": "Burg für Meeting in der Schweiz",
        "results_count": "2 Resultate"
    },
    {
        "url": "https://www.eventlokale.ch/locations/burg/hochzeit",
        "h1": "Burg für Hochzeit in der Schweiz",
        "results_count": "10 Resultate"
    },
    {
        "url": "https://www.eventlokale.ch/locations/burg/familienfeier",
        "h1": "Burg für Familienfeier in der Schweiz",
        "results_count": "11 Resultate"
    },
    {
        "url": "https://www.eventlokale.ch/locations/burg/privatanlass",
        "h1": "Burg für Privatanlass in der Schweiz",
        "results_count": "10 Resultate"
    },
    {
        "url": "https://www.eventlokale.ch/locations/burg/teamevent",
        "h1": "Burg für Teamevent in der Schweiz",
        "results_count": "3 Resultate"
    },
    {
        "url": "https://www.eventlokale.ch/locations/burg/party",
        "h1": "Burg für Party, Feier in der Schweiz",
        "results_count": "2 Resultate"
    },
    {
        "url": "https://www.eventlokale.ch/locations/burg/apero",
        "h1": "Burg für Apéro in der Schweiz",
        "results_count": "5 Resultate"
    },
    {
        "url": "https://www.eventlokale.ch/locations/burg/konzert",
        "h1": "Burg für Konzert in der Schweiz",
        "results_count": "3 Resultate"
    },
    {
        "url": "https://www.eventlokale.ch/locations/burg/theater-1",
        "h1": "Burg für Theater in der Schweiz",
        "results_count": "1 Resultat"
    },
    {
        "url": "https://www.eventlokale.ch/locations/burg/messe_ausstellung",
        "h1": "Burg für Messe, Ausstellung in der Schweiz",
        "results_count": "0 Resultat"
    },
    {
        "url": "https://www.eventlokale.ch/locations/burg/weihnachtsfeier",
        "h1": "Burg für Weihnachtsfeier in der Schweiz",
        "results_count": "1 Resultat"
    },
    {
        "url": "https://www.eventlokale.ch/locations/burg/klassentreffen",
        "h1": "Burg für Klassentreffen in der Schweiz",
        "results_count": "0 Resultat"
    },
    {
        "url": "https://www.eventlokale.ch/locations/burg/party-1",
        "h1": "Burg für Party in der Schweiz",
        "results_count": "0 Resultat"
    },
    {
        "url": "https://www.eventlokale.ch/locations/burg/sportanlass",
        "h1": "Burg für Sportanlass in der Schweiz",
        "results_count": "1 Resultat"
    },
    {
        "url": "https://www.eventlokale.ch/locations/burg/oeffentlicher_anlass",
        "h1": "Burg für Öffentlicher Anlass in der Schweiz",
        "results_count": "0 Resultat"
    },
    {
        "url": "https://www.eventlokale.ch/locations/cafe/vereinsanlass",
        "h1": "Café für Vereinsanlass in der Schweiz",
        "results_count": "8 Resultate"
    }
]